Workbook

Sheet PETUNJUK
B2: KALKULATOR COST & HARGA JUAL
B3: Divisi Handling - Lancar Jaya (LA & Handling Services)
B4: Versi 1.0 - Agustus 2026 | Khusus Divisi Handling (LA menyusul terpisah)
B6: CARA PAKAI
B7: Langkah 1 | C7: Buka sheet KALKULATOR. Isi Bagian A (Parameter Paket): jumlah pax, durasi, jumlah hotel, dll.
B8: Langkah 2 | C8: Di Bagian B, pilih YA/TIDAK untuk tiap layanan, dan isi kolom Qty (jumlah unit).
B9: Langkah 3 | C9: Lihat Bagian C (Rekap) - cost dan harga jual keluar otomatis.
B10: Langkah 4 | C10: Buka sheet PROFIT untuk melihat distribusi bagi hasil.
B11: Ubah tarif? | C11: Buka sheet KATALOG. Semua tarif ada di sana dan bisa diedit langsung.
B12: Tambah item? | C12: Isi baris kosong di bagian TAMBAHAN pada sheet KATALOG dan KALKULATOR.
B14: LEGENDA WARNA
B15: Kuning + teks biru | C15: SEL YANG ANDA ISI. Ini input utama - ubah sesuai kebutuhan.
B16: Teks biru | C16: Angka tarif yang bisa diedit (di sheet KATALOG).
B17: Teks hitam | C17: Hasil rumus otomatis. JANGAN DIUBAH.
B18: Teks hijau | C18: Rumus yang mengambil data dari sheet lain. JANGAN DIUBAH.
B19: Abu-abu tebal | C19: Baris total / subtotal.
B21: ISTILAH BASIS BIAYA
B22: PAX | C22: Biaya dikalikan jumlah jama'ah. Contoh: tips porter 20 SAR/pax x 40 pax = 800 SAR.
B23: FLAT | C23: Biaya tetap, tidak terpengaruh jumlah jama'ah. Contoh: fee freelancer 200 SAR.
B24: Qty | C24: Jumlah unit. Contoh: Snack City Tour Qty 2 = dua kali sesi city tour.
B26: CATATAN PENTING
B27: - | C27: Seluruh angka dalam SAR. Kurs SAR-IDR diisi di sheet KALKULATOR dan wajib dicek ulang saat transaksi.
B28: - | C28: Divisi Layanan Khusus & Insidental (jama'ah sakit, wafat, job insidental) TIDAK masuk kalkulator ini karena sifatnya pass-through - ditagihkan terpisah ke client.
B29: - | C29: Biaya legalitas, administrasi PT, konsultan pajak, dan marketing TIDAK masuk overhead - dibebankan ke profit (lihat sheet PROFIT).
B30: - | C30: Sifat biaya layanan Kursi Roda: Proses Umroh = per sesi per jama'ah; Harian = per hari per jama'ah. Isi Qty = jumlah sesi/hari x jumlah jama'ah pengguna.
B31: - | C31: Angka default yang terisi adalah paket standar 40 pax, 9 hari, 2 hotel, katering reguler.

Sheet KATALOG
B2: KATALOG TARIF - DIVISI HANDLING
B3: Semua tarif di bawah bisa diedit. Ubah angka biru, seluruh kalkulator ikut menyesuaikan.
B5: Kode | C5: Komponen | D5: Basis | E5: Rate Standar | F5: Rate Maksimal | G5: Rate Aktif | H5: Catatan
B6: A. HANDLING BANDARA & HOTEL
B7: H01 | C7: Fee Freelancer - Bandara Kedatangan | D7: FLAT | E7: 200 | F7: 200 | G7: =IF(KALKULATOR!$C$12="Maksimal",F7,E7) -> 200 | H7: Per job
B8: H02 | C8: Ongkos Transport PP - Kedatangan | D8: FLAT | E8: 260 | F8: 260 | G8: =IF(KALKULATOR!$C$12="Maksimal",F8,E8) -> 260 | H8: Per job
B9: H03 | C9: Tips Porter - Kedatangan | D9: PAX | E9: 20 | F9: 20 | G9: =IF(KALKULATOR!$C$12="Maksimal",F9,E9) -> 20 | H9: Jeddah T1 bisa 10 SAR/pax
B10: H04 | C10: Tips Muasasah - Kedatangan | D10: FLAT | E10: 20 | F10: 50 | G10: =IF(KALKULATOR!$C$12="Maksimal",F10,E10) -> 20 | H10: Nego
B11: H05 | C11: Fee Freelancer - Check-in Hotel | D11: FLAT | E11: 250 | F11: 250 | G11: =IF(KALKULATOR!$C$12="Maksimal",F11,E11) -> 250 | H11: Per hotel
B12: H06 | C12: Tips Bellboy - Check-in | D12: FLAT | E12: 70 | F12: 100 | G12: =IF(KALKULATOR!$C$12="Maksimal",F12,E12) -> 70 | H12: Per hotel, nego
B13: H07 | C13: Fee Freelancer - Check-out Hotel | D13: FLAT | E13: 200 | F13: 200 | G13: =IF(KALKULATOR!$C$12="Maksimal",F13,E13) -> 200 | H13: Per hotel
B14: H08 | C14: Tips Bellboy - Check-out | D14: FLAT | E14: 80 | F14: 150 | G14: =IF(KALKULATOR!$C$12="Maksimal",F14,E14) -> 80 | H14: Per hotel, nego
B15: H09 | C15: Tips Muasasah - Check-out | D15: FLAT | E15: 20 | F15: 50 | G15: =IF(KALKULATOR!$C$12="Maksimal",F15,E15) -> 20 | H15: 1x per trip, nego
B16: H10 | C16: Fee Freelancer - Bandara Kepulangan | D16: FLAT | E16: 250 | F16: 250 | G16: =IF(KALKULATOR!$C$12="Maksimal",F16,E16) -> 250 | H16: Per job
B17: H11 | C17: Ongkos Transport PP - Kepulangan | D17: FLAT | E17: 260 | F17: 260 | G17: =IF(KALKULATOR!$C$12="Maksimal",F17,E17) -> 260 | H17: Per job
B18: H12 | C18: Tips Porter - Kepulangan | D18: PAX | E18: 20 | F18: 20 | G18: =IF(KALKULATOR!$C$12="Maksimal",F18,E18) -> 20 | H18: Jeddah T1 bisa 10 SAR/pax
B19: H13 | C19: Tips Petugas Zamzam | D19: FLAT | E19: 20 | F19: 20 | G19: =IF(KALKULATOR!$C$12="Maksimal",F19,E19) -> 20 | H19: Penataan galon di troli
B20: B. MUTHOWIF
B21: M01 | C21: Fee Muthowif (per hari) | D21: FLAT | E21: 250 | F21: 250 | G21: =IF(KALKULATOR!$C$12="Maksimal",F21,E21) -> 250 | H21: 1 orang per grup/bus
B22: M02 | C22: Ongkos Muthowif PP | D22: FLAT | E22: 300 | F22: 300 | G22: =IF(KALKULATOR!$C$12="Maksimal",F22,E22) -> 300 | H22: 150 x 2
B23: M03 | C23: Fee Muthowifah - Bimbingan Raudhoh | D23: FLAT | E23: 200 | F23: 200 | G23: =IF(KALKULATOR!$C$12="Maksimal",F23,E23) -> 200 | H23: 1x per trip
B24: M04 | C24: Kursi Roda - Proses Umroh (per sesi/jama'ah) | D24: FLAT | E24: 250 | F24: 250 | G24: =IF(KALKULATOR!$C$12="Maksimal",F24,E24) -> 250 | H24: Thawaf & Sa'i
B25: M05 | C25: Kursi Roda - Harian (per hari/jama'ah) | D25: FLAT | E25: 250 | F25: 250 | G25: =IF(KALKULATOR!$C$12="Maksimal",F25,E25) -> 250 | H25: Termasuk thawaf & sa'i
B26: C. KATERING & SNACK
B27: K01 | C27: Nasi Box - REGULER | D27: PAX | E27: 15 | F27: 15 | G27: =IF(KALKULATOR!$C$12="Maksimal",F27,E27) -> 15 | H27: Bandara-Kota
B28: K02 | C28: Nasi Box - PREMIUM | D28: PAX | E28: 20 | F28: 20 | G28: =IF(KALKULATOR!$C$12="Maksimal",F28,E28) -> 20 | H28: Bandara-Kota
B29: K03 | C29: Snack City Tour - REGULER | D29: PAX | E29: 6.5 | F29: 6.5 | G29: =IF(KALKULATOR!$C$12="Maksimal",F29,E29) -> 6.5 | H29: Per sesi
B30: K04 | C30: Snack City Tour - PREMIUM | D30: PAX | E30: 10 | F30: 10 | G30: =IF(KALKULATOR!$C$12="Maksimal",F30,E30) -> 10 | H30: Per sesi
B31: K05 | C31: Snack Madinah-Makkah - REGULER | D31: PAX | E31: 8 | F31: 8 | G31: =IF(KALKULATOR!$C$12="Maksimal",F31,E31) -> 8 | H31: Atau sebaliknya
B32: K06 | C32: Snack Madinah-Makkah - PREMIUM | D32: PAX | E32: 12 | F32: 12 | G32: =IF(KALKULATOR!$C$12="Maksimal",F32,E32) -> 12 | H32: Atau sebaliknya
B33: K07 | C33: Air Zamzam Galon 5L (bawa pulang) | D33: PAX | E33: 12.5 | F33: 12.5 | G33: =IF(KALKULATOR!$C$12="Maksimal",F33,E33) -> 12.5 | H33: Per jama'ah
B34: K08 | C34: Albaik Kepulangan | D34: PAX | E34: 25 | F34: 25 | G34: =IF(KALKULATOR!$C$12="Maksimal",F34,E34) -> 25 | H34: Add-on / paket premium
B35: K09 | C35: Welcoming Drink (zamzam + cup 50pcs) | D35: FLAT | E35: 22.5 | F35: 22.5 | G35: =IF(KALKULATOR!$C$12="Maksimal",F35,E35) -> 22.5 | H35: 1 galon cukup s/d 50 pax
B36: D. TIP DRIVER BUS
B37: D01 | C37: Tip Driver - Bandara ke Hotel | D37: FLAT | E37: 100 | F37: 100 | G37: =IF(KALKULATOR!$C$12="Maksimal",F37,E37) -> 100 | H37: Per trip
B38: D02 | C38: Tip Driver - City Tour (per sesi) | D38: FLAT | E38: 50 | F38: 50 | G38: =IF(KALKULATOR!$C$12="Maksimal",F38,E38) -> 50 | H38: Per sesi
B39: D03 | C39: Tip Driver - Madinah ke Makkah | D39: FLAT | E39: 100 | F39: 100 | G39: =IF(KALKULATOR!$C$12="Maksimal",F39,E39) -> 100 | H39: Atau sebaliknya
B40: D04 | C40: Tip Driver - Hotel ke Bandara | D40: FLAT | E40: 100 | F40: 100 | G40: =IF(KALKULATOR!$C$12="Maksimal",F40,E40) -> 100 | H40: Per trip
B41: E. PHOTOGRAPHY
B42: P01 | C42: Sesi Standar (CT/Nabawi/Umroh Wajib) | D42: FLAT | E42: 230 | F42: 230 | G42: =IF(KALKULATOR!$C$12="Maksimal",F42,E42) -> 230 | H42: Per sesi
B43: P02 | C43: Sesi CT Makkah + Umroh Kedua | D43: FLAT | E43: 250 | F43: 250 | G43: =IF(KALKULATOR!$C$12="Maksimal",F43,E43) -> 250 | H43: Per sesi
B44: P03 | C44: Sesi Jabal Khandamah (grup) | D44: FLAT | E44: 280 | F44: 280 | G44: =IF(KALKULATOR!$C$12="Maksimal",F44,E44) -> 280 | H44: Per sesi
B45: P04 | C45: Surcharge Kamera Profesional | D45: FLAT | E45: 50 | F45: 50 | G45: =IF(KALKULATOR!$C$12="Maksimal",F45,E45) -> 50 | H45: Hanya sesi berkamera
B46: F. PENDAMPINGAN & KONSULTASI KESEHATAN
B47: S01 | C47: Fee Tenaga Medis (1 sesi = 3 jam) | D47: FLAT | E47: 500 | F47: 500 | G47: =IF(KALKULATOR!$C$12="Maksimal",F47,E47) -> 500 | H47: Alat dibawa sendiri
B48: G. TAMBAHAN (ISI SENDIRI)
B49: X01 | D49: FLAT | E49: 0 | F49: 0 | G49: =IF(KALKULATOR!$C$12="Maksimal",F49,E49) -> 0
B50: X02 | D50: FLAT | E50: 0 | F50: 0 | G50: =IF(KALKULATOR!$C$12="Maksimal",F50,E50) -> 0
B51: X03 | D51: FLAT | E51: 0 | F51: 0 | G51: =IF(KALKULATOR!$C$12="Maksimal",F51,E51) -> 0
B52: X04 | D52: FLAT | E52: 0 | F52: 0 | G52: =IF(KALKULATOR!$C$12="Maksimal",F52,E52) -> 0
B53: X05 | D53: FLAT | E53: 0 | F53: 0 | G53: =IF(KALKULATOR!$C$12="Maksimal",F53,E53) -> 0
B54: X06 | D54: FLAT | E54: 0 | F54: 0 | G54: =IF(KALKULATOR!$C$12="Maksimal",F54,E54) -> 0
B55: X07 | D55: FLAT | E55: 0 | F55: 0 | G55: =IF(KALKULATOR!$C$12="Maksimal",F55,E55) -> 0
B56: X08 | D56: FLAT | E56: 0 | F56: 0 | G56: =IF(KALKULATOR!$C$12="Maksimal",F56,E56) -> 0
B58: CATATAN: Kolom 'Rate Aktif' otomatis memilih antara Rate Standar atau Rate Maksimal, mengikuti pilihan Skenario Tips di sheet KALKULATOR (sel C12). Untuk komponen yang tidak punya rentang nego, isi Rate Standar dan Rate Maksimal dengan angka yang sama. Basis PAX = dikalikan jumlah jama'ah. Basis FLAT = tidak dikalikan jumlah jama'ah.

Sheet KALKULATOR
B2: KALKULATOR COST & HARGA JUAL - DIVISI HANDLING
B3: Isi sel kuning. Sisanya otomatis.
B5: A. PARAMETER PAKET
B6: Jumlah Jama'ah (Pax) | C6: 40 | D6: Total jama'ah dalam grup
B7: Durasi Paket (hari) | C7: 9 | D7: Termasuk hari perjalanan
B8: Hari Muthowif Bertugas | C8: 7 | D8: Biasanya durasi paket dikurangi 2
B9: Jumlah Hotel - Check-in | C9: 2 | D9: Madinah & Makkah = 2
B10: Jumlah Hotel - Check-out | C10: 2 | D10: Madinah & Makkah = 2
B11: Kelas Katering | C11: Reguler | D11: Pilih: Reguler atau Premium
B12: Skenario Tips | C12: Standar | D12: Pilih: Standar atau Maksimal
B13: Overhead (%) | C13: 0.05 | D13: Atribut, laundry, komunikasi, transport koordinasi
B14: Buffer Risiko (%) | C14: 0.05 | D14: Delay, freelancer batal, nego tips gagal
B15: Target Margin (%) | C15: 0.2 | D15: Margin yang diinginkan atas harga jual
B16: Kurs SAR ke IDR | C16: 4800 | D16: Cek ulang saat transaksi
B18: B. PILIHAN LAYANAN - pilih YA/TIDAK dan isi Qty
B19: Komponen | C19: Aktif | D19: Qty | E19: Basis | F19: Rate (SAR) | G19: Subtotal (SAR) | H19: Per Pax
B20: HANDLING
B21: Fee Freelancer - Bandara Kedatangan | C21: YA | D21: 1 | E21: =KATALOG!D7 -> FLAT | F21: =KATALOG!G7 -> 200 | G21: =IF($C21="YA",$D21*$F21*IF($E21="PAX",$C$6,1),0) -> 200 | H21: =IF($C$6=0,0,G21/$C$6) -> 5
B22: Ongkos Transport PP - Kedatangan | C22: YA | D22: 1 | E22: =KATALOG!D8 -> FLAT | F22: =KATALOG!G8 -> 260 | G22: =IF($C22="YA",$D22*$F22*IF($E22="PAX",$C$6,1),0) -> 260 | H22: =IF($C$6=0,0,G22/$C$6) -> 6.5
B23: Tips Porter - Kedatangan | C23: YA | D23: 1 | E23: =KATALOG!D9 -> PAX | F23: =KATALOG!G9 -> 20 | G23: =IF($C23="YA",$D23*$F23*IF($E23="PAX",$C$6,1),0) -> 800 | H23: =IF($C$6=0,0,G23/$C$6) -> 20
B24: Tips Muasasah - Kedatangan | C24: YA | D24: 1 | E24: =KATALOG!D10 -> FLAT | F24: =KATALOG!G10 -> 20 | G24: =IF($C24="YA",$D24*$F24*IF($E24="PAX",$C$6,1),0) -> 20 | H24: =IF($C$6=0,0,G24/$C$6) -> 0.5
B25: Fee Freelancer - Check-in Hotel | C25: YA | D25: =$C$9 -> 2 | E25: =KATALOG!D11 -> FLAT | F25: =KATALOG!G11 -> 250 | G25: =IF($C25="YA",$D25*$F25*IF($E25="PAX",$C$6,1),0) -> 500 | H25: =IF($C$6=0,0,G25/$C$6) -> 12.5
B26: Tips Bellboy - Check-in | C26: YA | D26: =$C$9 -> 2 | E26: =KATALOG!D12 -> FLAT | F26: =KATALOG!G12 -> 70 | G26: =IF($C26="YA",$D26*$F26*IF($E26="PAX",$C$6,1),0) -> 140 | H26: =IF($C$6=0,0,G26/$C$6) -> 3.5
B27: Fee Freelancer - Check-out Hotel | C27: YA | D27: =$C$10 -> 2 | E27: =KATALOG!D13 -> FLAT | F27: =KATALOG!G13 -> 200 | G27: =IF($C27="YA",$D27*$F27*IF($E27="PAX",$C$6,1),0) -> 400 | H27: =IF($C$6=0,0,G27/$C$6) -> 10
B28: Tips Bellboy - Check-out | C28: YA | D28: =$C$10 -> 2 | E28: =KATALOG!D14 -> FLAT | F28: =KATALOG!G14 -> 80 | G28: =IF($C28="YA",$D28*$F28*IF($E28="PAX",$C$6,1),0) -> 160 | H28: =IF($C$6=0,0,G28/$C$6) -> 4
B29: Tips Muasasah - Check-out | C29: YA | D29: 1 | E29: =KATALOG!D15 -> FLAT | F29: =KATALOG!G15 -> 20 | G29: =IF($C29="YA",$D29*$F29*IF($E29="PAX",$C$6,1),0) -> 20 | H29: =IF($C$6=0,0,G29/$C$6) -> 0.5
B30: Fee Freelancer - Bandara Kepulangan | C30: YA | D30: 1 | E30: =KATALOG!D16 -> FLAT | F30: =KATALOG!G16 -> 250 | G30: =IF($C30="YA",$D30*$F30*IF($E30="PAX",$C$6,1),0) -> 250 | H30: =IF($C$6=0,0,G30/$C$6) -> 6.25
B31: Ongkos Transport PP - Kepulangan | C31: YA | D31: 1 | E31: =KATALOG!D17 -> FLAT | F31: =KATALOG!G17 -> 260 | G31: =IF($C31="YA",$D31*$F31*IF($E31="PAX",$C$6,1),0) -> 260 | H31: =IF($C$6=0,0,G31/$C$6) -> 6.5
B32: Tips Porter - Kepulangan | C32: YA | D32: 1 | E32: =KATALOG!D18 -> PAX | F32: =KATALOG!G18 -> 20 | G32: =IF($C32="YA",$D32*$F32*IF($E32="PAX",$C$6,1),0) -> 800 | H32: =IF($C$6=0,0,G32/$C$6) -> 20
B33: Tips Petugas Zamzam | C33: YA | D33: 1 | E33: =KATALOG!D19 -> FLAT | F33: =KATALOG!G19 -> 20 | G33: =IF($C33="YA",$D33*$F33*IF($E33="PAX",$C$6,1),0) -> 20 | H33: =IF($C$6=0,0,G33/$C$6) -> 0.5
B34: SUBTOTAL HANDLING | G34: =SUM(G21:G33) -> 3830 | H34: =IF($C$6=0,0,G34/$C$6) -> 95.75
B36: MUTHOWIF
B37: Fee Muthowif (per hari) | C37: YA | D37: =$C$8 -> 7 | E37: =KATALOG!D21 -> FLAT | F37: =KATALOG!G21 -> 250 | G37: =IF($C37="YA",$D37*$F37*IF($E37="PAX",$C$6,1),0) -> 1750 | H37: =IF($C$6=0,0,G37/$C$6) -> 43.75
B38: Ongkos Muthowif PP | C38: YA | D38: 1 | E38: =KATALOG!D22 -> FLAT | F38: =KATALOG!G22 -> 300 | G38: =IF($C38="YA",$D38*$F38*IF($E38="PAX",$C$6,1),0) -> 300 | H38: =IF($C$6=0,0,G38/$C$6) -> 7.5
B39: Fee Muthowifah - Bimbingan Raudhoh | C39: YA | D39: 1 | E39: =KATALOG!D23 -> FLAT | F39: =KATALOG!G23 -> 200 | G39: =IF($C39="YA",$D39*$F39*IF($E39="PAX",$C$6,1),0) -> 200 | H39: =IF($C$6=0,0,G39/$C$6) -> 5
B40: Kursi Roda - Proses Umroh (sesi x jama'ah) | C40: TIDAK | D40: 0 | E40: =KATALOG!D24 -> FLAT | F40: =KATALOG!G24 -> 250 | G40: =IF($C40="YA",$D40*$F40*IF($E40="PAX",$C$6,1),0) -> 0 | H40: =IF($C$6=0,0,G40/$C$6) -> 0
B41: Kursi Roda - Harian (hari x jama'ah) | C41: TIDAK | D41: 0 | E41: =KATALOG!D25 -> FLAT | F41: =KATALOG!G25 -> 250 | G41: =IF($C41="YA",$D41*$F41*IF($E41="PAX",$C$6,1),0) -> 0 | H41: =IF($C$6=0,0,G41/$C$6) -> 0
B42: SUBTOTAL MUTHOWIF | G42: =SUM(G37:G41) -> 2250 | H42: =IF($C$6=0,0,G42/$C$6) -> 56.25
B44: KATERING & SNACK
B45: Nasi Box (Bandara-Kota) | C45: YA | D45: 1 | E45: =IF($C$11="Premium",KATALOG!D28,KATALOG!D27) -> PAX | F45: =IF($C$11="Premium",KATALOG!G28,KATALOG!G27) -> 15 | G45: =IF($C45="YA",$D45*$F45*IF($E45="PAX",$C$6,1),0) -> 600 | H45: =IF($C$6=0,0,G45/$C$6) -> 15
B46: Snack City Tour | C46: YA | D46: 2 | E46: =IF($C$11="Premium",KATALOG!D30,KATALOG!D29) -> PAX | F46: =IF($C$11="Premium",KATALOG!G30,KATALOG!G29) -> 6.5 | G46: =IF($C46="YA",$D46*$F46*IF($E46="PAX",$C$6,1),0) -> 520 | H46: =IF($C$6=0,0,G46/$C$6) -> 13
B47: Snack Madinah-Makkah | C47: YA | D47: 1 | E47: =IF($C$11="Premium",KATALOG!D32,KATALOG!D31) -> PAX | F47: =IF($C$11="Premium",KATALOG!G32,KATALOG!G31) -> 8 | G47: =IF($C47="YA",$D47*$F47*IF($E47="PAX",$C$6,1),0) -> 320 | H47: =IF($C$6=0,0,G47/$C$6) -> 8
B48: Air Zamzam Galon 5L (bawa pulang) | C48: YA | D48: 1 | E48: =KATALOG!D33 -> PAX | F48: =KATALOG!G33 -> 12.5 | G48: =IF($C48="YA",$D48*$F48*IF($E48="PAX",$C$6,1),0) -> 500 | H48: =IF($C$6=0,0,G48/$C$6) -> 12.5
B49: Albaik Kepulangan | C49: TIDAK | D49: 1 | E49: =KATALOG!D34 -> PAX | F49: =KATALOG!G34 -> 25 | G49: =IF($C49="YA",$D49*$F49*IF($E49="PAX",$C$6,1),0) -> 0 | H49: =IF($C$6=0,0,G49/$C$6) -> 0
B50: Welcoming Drink (zamzam + cup) | C50: YA | D50: 1 | E50: =KATALOG!D35 -> FLAT | F50: =KATALOG!G35 -> 22.5 | G50: =IF($C50="YA",$D50*$F50*IF($E50="PAX",$C$6,1),0) -> 22.5 | H50: =IF($C$6=0,0,G50/$C$6) -> 0.5625
B51: SUBTOTAL KATERING & SNACK | G51: =SUM(G45:G50) -> 1962.5 | H51: =IF($C$6=0,0,G51/$C$6) -> 49.0625
B53: TIP DRIVER BUS
B54: Tip Driver - Bandara ke Hotel | C54: YA | D54: 1 | E54: =KATALOG!D37 -> FLAT | F54: =KATALOG!G37 -> 100 | G54: =IF($C54="YA",$D54*$F54*IF($E54="PAX",$C$6,1),0) -> 100 | H54: =IF($C$6=0,0,G54/$C$6) -> 2.5
B55: Tip Driver - City Tour | C55: YA | D55: 2 | E55: =KATALOG!D38 -> FLAT | F55: =KATALOG!G38 -> 50 | G55: =IF($C55="YA",$D55*$F55*IF($E55="PAX",$C$6,1),0) -> 100 | H55: =IF($C$6=0,0,G55/$C$6) -> 2.5
B56: Tip Driver - Madinah ke Makkah | C56: YA | D56: 1 | E56: =KATALOG!D39 -> FLAT | F56: =KATALOG!G39 -> 100 | G56: =IF($C56="YA",$D56*$F56*IF($E56="PAX",$C$6,1),0) -> 100 | H56: =IF($C$6=0,0,G56/$C$6) -> 2.5
B57: Tip Driver - Hotel ke Bandara | C57: YA | D57: 1 | E57: =KATALOG!D40 -> FLAT | F57: =KATALOG!G40 -> 100 | G57: =IF($C57="YA",$D57*$F57*IF($E57="PAX",$C$6,1),0) -> 100 | H57: =IF($C$6=0,0,G57/$C$6) -> 2.5
B58: SUBTOTAL TIP DRIVER BUS | G58: =SUM(G54:G57) -> 400 | H58: =IF($C$6=0,0,G58/$C$6) -> 10
B60: PHOTOGRAPHY
B61: Sesi Standar (CT/Nabawi/Umroh Wajib) | C61: TIDAK | D61: 0 | E61: =KATALOG!D42 -> FLAT | F61: =KATALOG!G42 -> 230 | G61: =IF($C61="YA",$D61*$F61*IF($E61="PAX",$C$6,1),0) -> 0 | H61: =IF($C$6=0,0,G61/$C$6) -> 0
B62: Sesi CT Makkah + Umroh Kedua | C62: TIDAK | D62: 0 | E62: =KATALOG!D43 -> FLAT | F62: =KATALOG!G43 -> 250 | G62: =IF($C62="YA",$D62*$F62*IF($E62="PAX",$C$6,1),0) -> 0 | H62: =IF($C$6=0,0,G62/$C$6) -> 0
B63: Sesi Jabal Khandamah | C63: TIDAK | D63: 0 | E63: =KATALOG!D44 -> FLAT | F63: =KATALOG!G44 -> 280 | G63: =IF($C63="YA",$D63*$F63*IF($E63="PAX",$C$6,1),0) -> 0 | H63: =IF($C$6=0,0,G63/$C$6) -> 0
B64: Surcharge Kamera Profesional | C64: TIDAK | D64: 0 | E64: =KATALOG!D45 -> FLAT | F64: =KATALOG!G45 -> 50 | G64: =IF($C64="YA",$D64*$F64*IF($E64="PAX",$C$6,1),0) -> 0 | H64: =IF($C$6=0,0,G64/$C$6) -> 0
B65: SUBTOTAL PHOTOGRAPHY | G65: =SUM(G61:G64) -> 0 | H65: =IF($C$6=0,0,G65/$C$6) -> 0
B67: PENDAMPINGAN & KONSULTASI KESEHATAN
B68: Fee Tenaga Medis (per sesi) | C68: TIDAK | D68: 0 | E68: =KATALOG!D47 -> FLAT | F68: =KATALOG!G47 -> 500 | G68: =IF($C68="YA",$D68*$F68*IF($E68="PAX",$C$6,1),0) -> 0 | H68: =IF($C$6=0,0,G68/$C$6) -> 0
B69: SUBTOTAL PENDAMPINGAN & KONSULTASI KESEHATAN | G69: =SUM(G68:G68) -> 0 | H69: =IF($C$6=0,0,G69/$C$6) -> 0
B71: TAMBAHAN
B72: [Tambahan 1 - isi di sheet KATALOG] | C72: TIDAK | D72: 0 | E72: =KATALOG!D49 -> FLAT | F72: =KATALOG!G49 -> 0 | G72: =IF($C72="YA",$D72*$F72*IF($E72="PAX",$C$6,1),0) -> 0 | H72: =IF($C$6=0,0,G72/$C$6) -> 0
B73: [Tambahan 2 - isi di sheet KATALOG] | C73: TIDAK | D73: 0 | E73: =KATALOG!D50 -> FLAT | F73: =KATALOG!G50 -> 0 | G73: =IF($C73="YA",$D73*$F73*IF($E73="PAX",$C$6,1),0) -> 0 | H73: =IF($C$6=0,0,G73/$C$6) -> 0
B74: [Tambahan 3 - isi di sheet KATALOG] | C74: TIDAK | D74: 0 | E74: =KATALOG!D51 -> FLAT | F74: =KATALOG!G51 -> 0 | G74: =IF($C74="YA",$D74*$F74*IF($E74="PAX",$C$6,1),0) -> 0 | H74: =IF($C$6=0,0,G74/$C$6) -> 0
B75: [Tambahan 4 - isi di sheet KATALOG] | C75: TIDAK | D75: 0 | E75: =KATALOG!D52 -> FLAT | F75: =KATALOG!G52 -> 0 | G75: =IF($C75="YA",$D75*$F75*IF($E75="PAX",$C$6,1),0) -> 0 | H75: =IF($C$6=0,0,G75/$C$6) -> 0
B76: [Tambahan 5 - isi di sheet KATALOG] | C76: TIDAK | D76: 0 | E76: =KATALOG!D53 -> FLAT | F76: =KATALOG!G53 -> 0 | G76: =IF($C76="YA",$D76*$F76*IF($E76="PAX",$C$6,1),0) -> 0 | H76: =IF($C$6=0,0,G76/$C$6) -> 0
B77: [Tambahan 6 - isi di sheet KATALOG] | C77: TIDAK | D77: 0 | E77: =KATALOG!D54 -> FLAT | F77: =KATALOG!G54 -> 0 | G77: =IF($C77="YA",$D77*$F77*IF($E77="PAX",$C$6,1),0) -> 0 | H77: =IF($C$6=0,0,G77/$C$6) -> 0
B78: [Tambahan 7 - isi di sheet KATALOG] | C78: TIDAK | D78: 0 | E78: =KATALOG!D55 -> FLAT | F78: =KATALOG!G55 -> 0 | G78: =IF($C78="YA",$D78*$F78*IF($E78="PAX",$C$6,1),0) -> 0 | H78: =IF($C$6=0,0,G78/$C$6) -> 0
B79: [Tambahan 8 - isi di sheet KATALOG] | C79: TIDAK | D79: 0 | E79: =KATALOG!D56 -> FLAT | F79: =KATALOG!G56 -> 0 | G79: =IF($C79="YA",$D79*$F79*IF($E79="PAX",$C$6,1),0) -> 0 | H79: =IF($C$6=0,0,G79/$C$6) -> 0
B80: SUBTOTAL TAMBAHAN | G80: =SUM(G72:G79) -> 0 | H80: =IF($C$6=0,0,G80/$C$6) -> 0
B82: C. REKAP COST & HARGA JUAL
B83: Keterangan | G83: Total (SAR) | H83: Per Pax (SAR)
B84: DIRECT COST | G84: =G34+G42+G51+G58+G65+G69+G80 -> 8442.5 | H84: =IF($C$6=0,0,G84/$C$6) -> 211.0625
B85: (+) Overhead | G85: =G84*$C$13 -> 422.125 | H85: =IF($C$6=0,0,G85/$C$6) -> 10.553125
B86: (+) Buffer Risiko | G86: =G84*$C$14 -> 422.125 | H86: =IF($C$6=0,0,G86/$C$6) -> 10.553125
B87: FULL COST | G87: =SUM(G84:G86) -> 9286.75 | H87: =IF($C$6=0,0,G87/$C$6) -> 232.16875
B89: HARGA JUAL (berdasarkan Target Margin di sel C15)
B90: HARGA JUAL | G90: =IF($C$15>=1,0,G87/(1-$C$15)) -> 11608.438 | H90: =IF($C$6=0,0,G90/$C$6) -> 290.21094
B91: PROFIT | G91: =G90-G87 -> 2321.6875 | H91: =IF($C$6=0,0,G91/$C$6) -> 58.042187
B92: Margin Tercapai (kontrol) | G92: =IF(G90=0,0,G91/G90) -> 0.2
B93: Markup atas Cost (kontrol) | G93: =IF(G87=0,0,G91/G87) -> 0.25
B95: KONVERSI RUPIAH
B96: Full Cost (IDR) | G96: =G87*$C$16 -> 44576400 | H96: =IF($C$6=0,0,G96/$C$6) -> 1114410
B97: Harga Jual (IDR) | G97: =G90*$C$16 -> 55720500 | H97: =IF($C$6=0,0,G97/$C$6) -> 1393012.5
B98: Profit (IDR) | G98: =G91*$C$16 -> 11144100 | H98: =IF($C$6=0,0,G98/$C$6) -> 278602.5
B100: D. SKENARIO HARGA JUAL PER TARGET MARGIN
B101: Target Margin | C101: Harga Jual/Pax (SAR) | D101: Harga Jual/Pax (IDR) | E101: Profit/Pax (SAR) | F101: Profit Grup (SAR)
B102: 0.1 | C102: =IF($C$6=0,0,(G87/(1-B102))/$C$6) -> 257.96528 | D102: =C102*$C$16 -> 1238233.3 | E102: =C102-IF($C$6=0,0,G87/$C$6) -> 25.796528 | F102: =(G87/(1-B102))-G87 -> 1031.8611
B103: 0.125 | C103: =IF($C$6=0,0,(G87/(1-B103))/$C$6) -> 265.33571 | D103: =C103*$C$16 -> 1273611.4 | E103: =C103-IF($C$6=0,0,G87/$C$6) -> 33.166964 | F103: =(G87/(1-B103))-G87 -> 1326.6786
B104: 0.15 | C104: =IF($C$6=0,0,(G87/(1-B104))/$C$6) -> 273.13971 | D104: =C104*$C$16 -> 1311070.6 | E104: =C104-IF($C$6=0,0,G87/$C$6) -> 40.970956 | F104: =(G87/(1-B104))-G87 -> 1638.8382
B105: 0.175 | C105: =IF($C$6=0,0,(G87/(1-B105))/$C$6) -> 281.41667 | D105: =C105*$C$16 -> 1350800 | E105: =C105-IF($C$6=0,0,G87/$C$6) -> 49.247917 | F105: =(G87/(1-B105))-G87 -> 1969.9167
B106: 0.2 | C106: =IF($C$6=0,0,(G87/(1-B106))/$C$6) -> 290.21094 | D106: =C106*$C$16 -> 1393012.5 | E106: =C106-IF($C$6=0,0,G87/$C$6) -> 58.042187 | F106: =(G87/(1-B106))-G87 -> 2321.6875
B107: 0.225 | C107: =IF($C$6=0,0,(G87/(1-B107))/$C$6) -> 299.57258 | D107: =C107*$C$16 -> 1437948.4 | E107: =C107-IF($C$6=0,0,G87/$C$6) -> 67.403831 | F107: =(G87/(1-B107))-G87 -> 2696.1532
B108: 0.25 | C108: =IF($C$6=0,0,(G87/(1-B108))/$C$6) -> 309.55833 | D108: =C108*$C$16 -> 1485880 | E108: =C108-IF($C$6=0,0,G87/$C$6) -> 77.389583 | F108: =(G87/(1-B108))-G87 -> 3095.5833
B109: 0.3 | C109: =IF($C$6=0,0,(G87/(1-B109))/$C$6) -> 331.66964 | D109: =C109*$C$16 -> 1592014.3 | E109: =C109-IF($C$6=0,0,G87/$C$6) -> 99.500893 | F109: =(G87/(1-B109))-G87 -> 3980.0357

Sheet PROFIT
B2: DISTRIBUSI PROFIT
B3: Mengambil angka Profit dari sheet KALKULATOR (per 1 grup)
B5: A. URUTAN PEMBAGIAN (per 1 grup)
B6: Keterangan | C6: SAR | D6: IDR
B7: Profit Kotor (dari KALKULATOR) | C7: =KALKULATOR!G91 -> 2321.6875 | D7: =C7*KALKULATOR!$C$16 -> 11144100
B8: (-) Biaya di luar anggaran (legalitas, konsultan, marketing) | C8: 0 | D8: =C8*KALKULATOR!$C$16 -> 0
B9: PROFIT BERSIH OPERASIONAL | C9: =C7-C8 -> 2321.6875 | D9: =C9*KALKULATOR!$C$16 -> 11144100
B10: (-) Gaji Direktur (35%) | C10: =C9*0.35 -> 812.59063 | D10: =C10*KALKULATOR!$C$16 -> 3900435
B11: Laba Kena Pajak | C11: =C9-C10 -> 1509.0969 | D11: =C11*KALKULATOR!$C$16 -> 7243665
B12: Tarif PPh Badan (%) | C12: 0.11 | D12: Pasal 31E: 11% untuk omzet s/d Rp 4,8 M
B13: (-) PPh Badan | C13: =C11*C12 -> 166.00066 | D13: =C13*KALKULATOR!$C$16 -> 796803.15
B14: LABA BERSIH | C14: =C11-C13 -> 1343.0962 | D14: =C14*KALKULATOR!$C$16 -> 6446861.8
B16: B. GAJI DIREKTUR (35% dari Profit Bersih Operasional)
B17: Personel / Jabatan | C17: SAR | D17: IDR
B18: Ocid - Dirut + Direktur LA | C18: =C9*0.14 -> 325.03625 | D18: =C18*KALKULATOR!$C$16 -> 1560174
B19: Azzam - Dir. Handling + Dir. Marketing | C19: =C9*0.14 -> 325.03625 | D19: =C19*KALKULATOR!$C$16 -> 1560174
B20: Andika - Direktur Keuangan | C20: =C9*0.07 -> 162.51812 | D20: =C20*KALKULATOR!$C$16 -> 780087
B21: TOTAL GAJI DIREKTUR | C21: =SUM(C18:C20) -> 812.59063 | D21: =C21*KALKULATOR!$C$16 -> 3900435
B23: C. PEMBAGIAN LABA BERSIH
B24: Pos | C24: SAR | D24: IDR
B25: Tabungan / Dana Darurat (23%) | C25: =C14*0.23 -> 308.91213 | D25: =C25*KALKULATOR!$C$16 -> 1482778.2
B26: Dividen Owner (77%) - dibagi tiap 6 bulan | C26: =C14*0.77 -> 1034.1841 | D26: =C26*KALKULATOR!$C$16 -> 4964083.6
B28: D. PROYEKSI TAHUNAN
B29: Jumlah Grup per Bulan | C29: 4
B30: Jumlah Grup per Tahun | C30: =C29*12 -> 48
B31: Pos | C31: Per Tahun (SAR) | D31: Per Tahun (IDR)
B32: Profit Bersih Operasional | C32: =C9*C30 -> 111441 | D32: =C32*KALKULATOR!$C$16 -> 534916800
B33: Gaji Ocid | C33: =C18*C30 -> 15601.74 | D33: =C33*KALKULATOR!$C$16 -> 74888352
B34: Gaji Azzam | C34: =C19*C30 -> 15601.74 | D34: =C34*KALKULATOR!$C$16 -> 74888352
B35: Gaji Andika | C35: =C20*C30 -> 7800.87 | D35: =C35*KALKULATOR!$C$16 -> 37444176
B36: PPh Badan | C36: =C13*C30 -> 7968.0315 | D36: =C36*KALKULATOR!$C$16 -> 38246551
B37: Laba Bersih | C37: =C14*C30 -> 64468.618 | D37: =C37*KALKULATOR!$C$16 -> 3.0944937e+08
B38: Tabungan | C38: =C25*C30 -> 14827.782 | D38: =C38*KALKULATOR!$C$16 -> 71173355
B39: Dividen Owner | C39: =C26*C30 -> 49640.836 | D39: =C39*KALKULATOR!$C$16 -> 2.3827601e+08
B41: CATATAN: 1. Gaji Direktur diperlakukan sebagai BIAYA perusahaan, sehingga mengurangi laba kena pajak. 2. PPh Badan dihitung SEBELUM pembagian Tabungan & Dividen. Ini mencegah kekurangan dana saat pembagian. 3. Proporsi Tabungan : Dividen = 23% : 77% (setara 15% : 50% dari profit sebelum pajak). 4. Biaya legalitas, administrasi PT, konsultan pajak, dan marketing diisi di baris 'Biaya di luar anggaran'. 5. Angka pajak di sini hanya estimasi kasar - wajib dikonfirmasi ke konsultan pajak.
